hydra_configs/pytorch_lightning/__init__.py
hydra_configs/pytorch_lightning/callbacks.py
hydra_configs/pytorch_lightning/metrics/__init__.py
hydra_configs/pytorch_lightning/metrics/classification.py
hydra_configs/pytorch_lightning/metrics/regression.py
hydra_configs/pytorch_lightning/trainer.py
hydra_configs_pytorch_lightning-0.1.0.dist-info/entry_points.txt
hydra_configs_pytorch_lightning-0.1.0.dist-info/LICENSE
hydra_configs_pytorch_lightning-0.1.0.dist-info/WHEEL
hydra_configs_pytorch_lightning-0.1.0.dist-info/METADATA
hydra_configs_pytorch_lightning-0.1.0.dist-info/RECORD
