Metadata-Version: 2.1
Name: hydra-configs-pytorch-lightning
Version: 0.1.0
Summary: Hydra Lightning
Home-page: https://github.com/romesco/hydra-lightning
License: MIT
Author: Rosario Scalise
Author-email: rosario@cs.uw.edu
Requires-Python: >=3.7,<4.0
Classifier: License :: OSI Approved :: MIT License
Classifier: Programming Language :: Python :: 3
Classifier: Programming Language :: Python :: 3.7
Classifier: Programming Language :: Python :: 3.8
Classifier: Programming Language :: Python :: 3.9
Project-URL: Changelog, https://github.com/romesco/hydra-lightning/releases
Project-URL: Documentation, https://github.com/romesco/README.md
Project-URL: Repository, https://github.com/romesco/hydra-lightning
